test_topicmodel.py
topicmodel-0.1.2.dist-info/METADATA
topicmodel-0.1.2.dist-info/WHEEL
topicmodel-0.1.2.dist-info/entry_points.txt
topicmodel-0.1.2.dist-info/licenses/LICENSE
topicmodel.py
topicmodel-0.1.2.dist-info/RECORD
