Metadata-Version: 2.1
Name: topicmodel
Version: 0.1.2
Summary: Semantic document clustering and topic labeling
Author-Email: S Anand <root.node@gmail.com>
License: MIT
Requires-Python: >=3.12
Requires-Dist: httpx>=0.27
Requires-Dist: pandas
Requires-Dist: numpy
Requires-Dist: scikit-learn
Requires-Dist: tiktoken
Requires-Dist: tqdm
